typedtuples/__init__.py
typedtuples/typedtuples.py
typedtuples/utils.py
Typedtuples-1.0.7.dist-info/METADATA
Typedtuples-1.0.7.dist-info/WHEEL
Typedtuples-1.0.7.dist-info/top_level.txt
Typedtuples-1.0.7.dist-info/RECORD
