Metadata-Version: 2.1
Name: Typedtuples
Version: 1.0.7
Summary: Namedtuple with Strict Type Checking
Home-page: https://github.com/pl-Steve28-lq/TypedTuples
Author: Steve28
Author-email: holiday28784@gmail.com
License: UNKNOWN
Platform: UNKNOWN
Classifier: Programming Language :: Python :: 3
Classifier: License :: OSI Approved :: MIT License
Classifier: Operating System :: OS Independent
Requires-Python: >=3.6
